odoo/addons/delivery_driver/README.rst
odoo/addons/delivery_driver/__init__.py
odoo/addons/delivery_driver/__manifest__.py
odoo/addons/delivery_driver/i18n/delivery_driver.pot
odoo/addons/delivery_driver/i18n/es.po
odoo/addons/delivery_driver/i18n/it.po
odoo/addons/delivery_driver/models/__init__.py
odoo/addons/delivery_driver/models/delivery_carrier.py
odoo/addons/delivery_driver/models/res_partner.py
odoo/addons/delivery_driver/models/stock_move_line.py
odoo/addons/delivery_driver/models/stock_picking.py
odoo/addons/delivery_driver/readme/CONTEXT.md
odoo/addons/delivery_driver/readme/CONTRIBUTORS.md
odoo/addons/delivery_driver/readme/DESCRIPTION.md
odoo/addons/delivery_driver/readme/USAGE.md
odoo/addons/delivery_driver/static/description/icon.png
odoo/addons/delivery_driver/static/description/index.html
odoo/addons/delivery_driver/tests/__init__.py
odoo/addons/delivery_driver/tests/test_delivery_driver.py
odoo/addons/delivery_driver/views/delivery_carrier.xml
odoo/addons/delivery_driver/views/res_partner.xml
odoo/addons/delivery_driver/views/stock_move_line.xml
odoo/addons/delivery_driver/views/stock_picking.xml
odoo_addon_delivery_driver-18.0.1.0.1.5.dist-info/METADATA
odoo_addon_delivery_driver-18.0.1.0.1.5.dist-info/WHEEL
odoo_addon_delivery_driver-18.0.1.0.1.5.dist-info/top_level.txt
odoo_addon_delivery_driver-18.0.1.0.1.5.dist-info/RECORD
